artificial/substrate/__init__.py
artificial/substrate/client.py
artificial-0.0.2.dist-info/LICENSE
artificial-0.0.2.dist-info/METADATA
artificial-0.0.2.dist-info/WHEEL
artificial-0.0.2.dist-info/top_level.txt
artificial-0.0.2.dist-info/RECORD
