Metadata-Version: 2.1
Name: artificial
Version: 0.0.2
Summary: Artificial tools
Home-page: UNKNOWN
Author: Artificial team
Author-email: info@artificial.com
License: UNKNOWN
Platform: UNKNOWN
Classifier: Programming Language :: Python :: 3
Classifier: License :: OSI Approved :: MIT License
Classifier: Operating System :: POSIX :: Linux
Requires-Python: ~=3.6
